contactform/__init__.py
contactform/apps.py
contactform/forms.py
contactform/tests.py
contactform/urls.py
contactform/views.py
contactform/locale/en/LC_MESSAGES/django.mo
contactform/locale/en/LC_MESSAGES/django.po
contactform/locale/fr/LC_MESSAGES/django.mo
contactform/locale/fr/LC_MESSAGES/django.po
contactform/migrations/__init__.py
contactform/templates/contactform/base.html
contactform/templates/contactform/contact.html
contactform/templates/contactform/form.html
contactform/templates/contactform/form_bootstrap.html
contactform/templates/contactform/form_uikit.html
contactform/templates/contactform/message.txt
contactform/templates/contactform/thanks.html
contactform/templates/contactform/tags/contact_form.html
contactform/templatetags/__init__.py
contactform/templatetags/contact_form.py
django_contactform-2.2.1.dist-info/LICENSE.rst
django_contactform-2.2.1.dist-info/METADATA
django_contactform-2.2.1.dist-info/WHEEL
django_contactform-2.2.1.dist-info/top_level.txt
django_contactform-2.2.1.dist-info/RECORD
